typed_bencode/__init__.py
typed_bencode-0.0.1.dist-info/METADATA
typed_bencode-0.0.1.dist-info/WHEEL
typed_bencode-0.0.1.dist-info/top_level.txt
typed_bencode-0.0.1.dist-info/RECORD
